unique_code_generator/__init__.py
unique_code_generator/generator.py
unique_code_generator-0.1.0.dist-info/LICENSE
unique_code_generator-0.1.0.dist-info/METADATA
unique_code_generator-0.1.0.dist-info/WHEEL
unique_code_generator-0.1.0.dist-info/top_level.txt
unique_code_generator-0.1.0.dist-info/RECORD
